CHANGES.txt
LICENSE.txt
README.txt
setup.py
version.txt
raisin/__init__.py
raisin.recipe.transformation.egg-info/PKG-INFO
raisin.recipe.transformation.egg-info/SOURCES.txt
raisin.recipe.transformation.egg-info/dependency_links.txt
raisin.recipe.transformation.egg-info/entry_points.txt
raisin.recipe.transformation.egg-info/namespace_packages.txt
raisin.recipe.transformation.egg-info/not-zip-safe
raisin.recipe.transformation.egg-info/requires.txt
raisin.recipe.transformation.egg-info/top_level.txt
raisin/recipe/__init__.py
raisin/recipe/transformation/__init__.py
raisin/recipe/transformation/accessions.py
raisin/recipe/transformation/annotations.py
raisin/recipe/transformation/experiments.py
raisin/recipe/transformation/files.py
raisin/recipe/transformation/genomes.py
raisin/recipe/transformation/profiles.py
raisin/recipe/transformation/read_length.py
raisin/recipe/transformation/view.py
raisin/recipe/transformation/tests/README.txt
raisin/recipe/transformation/tests/__init__.py
raisin/recipe/transformation/tests/test_recipe.py
raisin/recipe/transformation/tests/sandbox/experiments.csv
raisin/recipe/transformation/tests/sandbox/read_length.csv
raisin/recipe/transformation/tests/sandbox/view.csv